LICENSE.txt
README.md
setup.cfg
setup.py
kobato/__init__.py
kobato/command_line.py
kobato/config.py
kobato/misc.py
kobato/plugin.py
kobato.egg-info/PKG-INFO
kobato.egg-info/SOURCES.txt
kobato.egg-info/dependency_links.txt
kobato.egg-info/entry_points.txt
kobato.egg-info/not-zip-safe
kobato.egg-info/requires.txt
kobato.egg-info/top_level.txt
kobato/commands/__init__.py
kobato/commands/alias.py
kobato/commands/login.py
kobato/commands/post.py
kobato/commands/show.py
kobato/commands/subscribe.py